[
  { "code": "AED", "name": "UAE Dirham", "description": "", "withdrawn": false },
  { "code": "AFN", "name": "Afghani", "description": "", "withdrawn": false },
  { "code": "ALL", "name": "Lek", "description": "", "withdrawn": false },
  { "code": "AMD", "name": "Armenian Dram", "description": "", "withdrawn": false },
  { "code": "ANG", "name": "Netherlands Antillian Guilder", "description": "", "withdrawn": false },
  { "code": "AOA", "name": "Kwanza", "description": "", "withdrawn": false },
  { "code": "ARS", "name": "Argentine Peso", "description": "", "withdrawn": false },
  { "code": "AUD", "name": "Australian Dollar", "description": "", "withdrawn": false },
  { "code": "AWG", "name": "Aruban Guilder", "description": "", "withdrawn": false },
  { "code": "AZN", "name": "Azerbaijanian Manat", "description": "", "withdrawn": false },
  { "code": "BAM", "name": "Convertible Marks", "description": "", "withdrawn": false },
  { "code": "BBD", "name": "Barbados Dollar", "description": "", "withdrawn": false },
  { "code": "BDT", "name": "Taka", "description": "", "withdrawn": false },
  { "code": "BGN", "name": "Bulgarian Lev", "description": "", "withdrawn": false },
  { "code": "BHD", "name": "Bahraini Dinar", "description": "", "withdrawn": false },
  { "code": "BIF", "name": "Burundi Franc", "description": "", "withdrawn": false },
  { "code": "BMD", "name": "Bermudian Dollar", "description": "", "withdrawn": false },
  { "code": "BND", "name": "Brunei Dollar", "description": "", "withdrawn": false },
  { "code": "BOB", "name": "Boliviano", "description": "", "withdrawn": false },
  { "code": "BOV", "name": "Mvdol", "description": "", "withdrawn": false },
  { "code": "BRL", "name": "Brazilian Real", "description": "", "withdrawn": false },
  { "code": "BSD", "name": "Bahamian Dollar", "description": "", "withdrawn": false },
  { "code": "BTN", "name": "Ngultrum", "description": "", "withdrawn": false },
  { "code": "BWP", "name": "Pula", "description": "", "withdrawn": false },
  { "code": "BYR", "name": "Belarussian Ruble", "description": "Withdrawn from ISO Currency codelist. Use code BYN.", "withdrawn": true },
  { "code": "BYN", "name": "Belarussian Ruble", "description": "", "withdrawn": false },
  { "code": "BZD", "name": "Belize Dollar", "description": "", "withdrawn": false },
  { "code": "CAD", "name": "Canadian Dollar", "description": "", "withdrawn": false },
  { "code": "CDF", "name": "Congolese Franc", "description": "", "withdrawn": false },
  { "code": "CHF", "name": "Swiss Franc", "description": "", "withdrawn": false },
  { "code": "CLF", "name": "Unidades de fomento", "description": "", "withdrawn": false },
  { "code": "CLP", "name": "Chilean Peso", "description": "", "withdrawn": false },
  { "code": "CNY", "name": "Yuan Renminbi", "description": "", "withdrawn": false },
  { "code": "COP", "name": "Colombian Peso", "description": "", "withdrawn": false },
  { "code": "COU", "name": "Unidad de Valor Real", "description": "", "withdrawn": false },
  { "code": "CRC", "name": "Costa Rican Colon", "description": "", "withdrawn": false },
  { "code": "CUC", "name": "Peso Convertible", "description": "", "withdrawn": false },
  { "code": "CUP", "name": "Cuban Peso", "description": "", "withdrawn": false },
  { "code": "CVE", "name": "Cape Verde Escudo", "description": "", "withdrawn": false },
  { "code": "CZK", "name": "Czech Koruna", "description": "", "withdrawn": false },
  { "code": "DJF", "name": "Djibouti Franc", "description": "", "withdrawn": false },
  { "code": "DKK", "name": "Danish Krone", "description": "", "withdrawn": false },
  { "code": "DOP", "name": "Dominican Peso", "description": "", "withdrawn": false },
  { "code": "DZD", "name": "Algerian Dinar", "description": "", "withdrawn": false },
  { "code": "EEK", "name": "Kroon", "description": "Withdrawn from ISO Currency codelist", "withdrawn": true },
  { "code": "EGP", "name": "Egyptian Pound", "description": "", "withdrawn": false },
  { "code": "ERN", "name": "Nakfa", "description": "", "withdrawn": false },
  { "code": "ETB", "name": "Ethiopian Birr", "description": "", "withdrawn": false },
  { "code": "EUR", "name": "Euro", "description": "", "withdrawn": false },
  { "code": "FJD", "name": "Fiji Dollar", "description": "", "withdrawn": false },
  { "code": "FKP", "name": "Falkland Islands Pound", "description": "", "withdrawn": false },
  { "code": "GBP", "name": "Pound Sterling", "description": "", "withdrawn": false },
  { "code": "GEL", "name": "Lari", "description": "", "withdrawn": false },
  { "code": "GHS", "name": "Cedi", "description": "", "withdrawn": false },
  { "code": "GIP", "name": "Gibraltar Pound", "description": "", "withdrawn": false },
  { "code": "GMD", "name": "Dalasi", "description": "", "withdrawn": false },
  { "code": "GNF", "name": "Guinea Franc", "description": "", "withdrawn": false },
  { "code": "GTQ", "name": "Quetzal", "description": "", "withdrawn": false },
  { "code": "GYD", "name": "Guyana Dollar", "description": "", "withdrawn": false },
  { "code": "HKD", "name": "Hong Kong Dollar", "description": "", "withdrawn": false },
  { "code": "HNL", "name": "Lempira", "description": "", "withdrawn": false },
  { "code": "HRK", "name": "Kuna", "description": "", "withdrawn": false },
  { "code": "HTG", "name": "Gourde", "description": "", "withdrawn": false },
  { "code": "HUF", "name": "Forint", "description": "", "withdrawn": false },
  { "code": "IDR", "name": "Rupiah", "description": "", "withdrawn": false },
  { "code": "ILS", "name": "New Israeli Sheqel", "description": "", "withdrawn": false },
  { "code": "INR", "name": "Indian Rupee", "description": "", "withdrawn": false },
  { "code": "IQD", "name": "Iraqi Dinar", "description": "", "withdrawn": false },
  { "code": "IRR", "name": "Iranian Rial", "description": "", "withdrawn": false },
  { "code": "ISK", "name": "Iceland Krona", "description": "", "withdrawn": false },
  { "code": "JMD", "name": "Jamaican Dollar", "description": "", "withdrawn": false },
  { "code": "JOD", "name": "Jordanian Dinar", "description": "", "withdrawn": false },
  { "code": "JPY", "name": "Yen", "description": "", "withdrawn": false },
  { "code": "KES", "name": "Kenyan Shilling", "description": "", "withdrawn": false },
  { "code": "KGS", "name": "Som", "description": "", "withdrawn": false },
  { "code": "KHR", "name": "Riel", "description": "", "withdrawn": false },
  { "code": "KMF", "name": "Comoro Franc", "description": "", "withdrawn": false },
  { "code": "KPW", "name": "North Korean Won", "description": "", "withdrawn": false },
  { "code": "KRW", "name": "Won", "description": "", "withdrawn": false },
  { "code": "KWD", "name": "Kuwaiti Dinar", "description": "", "withdrawn": false },
  { "code": "KYD", "name": "Cayman Islands Dollar", "description": "", "withdrawn": false },
  { "code": "KZT", "name": "Tenge", "description": "", "withdrawn": false },
  { "code": "LAK", "name": "Kip", "description": "", "withdrawn": false },
  { "code": "LBP", "name": "Lebanese Pound", "description": "", "withdrawn": false },
  { "code": "LKR", "name": "Sri Lanka Rupee", "description": "", "withdrawn": false },
  { "code": "LRD", "name": "Liberian Dollar", "description": "", "withdrawn": false },
  { "code": "LSL", "name": "Loti", "description": "", "withdrawn": false },
  { "code": "LTL", "name": "Lithuanian Litas", "description": "Withdrawn from ISO Currency codelist", "withdrawn": true },
  { "code": "LVL", "name": "Latvian Lats", "description": "Withdrawn from ISO Currency codelist", "withdrawn": true },
  { "code": "LYD", "name": "Libyan Dinar", "description": "", "withdrawn": false },
  { "code": "MAD", "name": "Moroccan Dirham", "description": "", "withdrawn": false },
  { "code": "MDL", "name": "Moldovan Leu", "description": "", "withdrawn": false },
  { "code": "MGA", "name": "Malagasy Ariary", "description": "", "withdrawn": false },
  { "code": "MKD", "name": "Denar", "description": "", "withdrawn": false },
  { "code": "MMK", "name": "Kyat", "description": "", "withdrawn": false },
  { "code": "MNT", "name": "Tugrik", "description": "", "withdrawn": false },
  { "code": "MOP", "name": "Pataca", "description": "", "withdrawn": false },
  { "code": "MRO", "name": "Ouguiya", "description": "Withdrawn from ISO Currency codelist. Use code MRU.", "withdrawn": true },
  { "code": "MRU", "name": "Ouguiya", "description": "", "withdrawn": false },
  { "code": "MUR", "name": "Mauritius Rupee", "description": "", "withdrawn": false },
  { "code": "MVR", "name": "Rufiyaa", "description": "", "withdrawn": false },
  { "code": "MWK", "name": "Malawi Kwacha", "description": "", "withdrawn": false },
  { "code": "MXN", "name": "Mexican Peso", "description": "", "withdrawn": false },
  { "code": "MXV", "name": "Mexican Unidad de Inversion (UDI)", "description": "", "withdrawn": false },
  { "code": "MYR", "name": "Malaysian Ringgit", "description": "", "withdrawn": false },
  { "code": "MZN", "name": "Metical", "description": "", "withdrawn": false },
  { "code": "NAD", "name": "Namibia Dollar", "description": "", "withdrawn": false },
  { "code": "NGN", "name": "Naira", "description": "", "withdrawn": false },
  { "code": "NIO", "name": "Cordoba Oro", "description": "", "withdrawn": false },
  { "code": "NOK", "name": "Norwegian Krone", "description": "", "withdrawn": false },
  { "code": "NPR", "name": "Nepalese Rupee", "description": "", "withdrawn": false },
  { "code": "NZD", "name": "New Zealand Dollar", "description": "", "withdrawn": false },
  { "code": "OMR", "name": "Rial Omani", "description": "", "withdrawn": false },
  { "code": "PAB", "name": "Balboa", "description": "", "withdrawn": false },
  { "code": "PEN", "name": "Nuevo Sol", "description": "", "withdrawn": false },
  { "code": "PGK", "name": "Kina", "description": "", "withdrawn": false },
  { "code": "PHP", "name": "Philippine Peso", "description": "", "withdrawn": false },
  { "code": "PKR", "name": "Pakistan Rupee", "description": "", "withdrawn": false },
  { "code": "PLN", "name": "Zloty", "description": "", "withdrawn": false },
  { "code": "PYG", "name": "Guarani", "description": "", "withdrawn": false },
  { "code": "QAR", "name": "Qatari Rial", "description": "", "withdrawn": false },
  { "code": "RON", "name": "Romanian Leu", "description": "", "withdrawn": false },
  { "code": "RSD", "name": "Serbian Dinar", "description": "", "withdrawn": false },
  { "code": "RUB", "name": "Russian Ruble", "description": "", "withdrawn": false },
  { "code": "RWF", "name": "Rwanda Franc", "description": "", "withdrawn": false },
  { "code": "SAR", "name": "Saudi Riyal", "description": "", "withdrawn": false },
  { "code": "SBD", "name": "Solomon Islands Dollar", "description": "", "withdrawn": false },
  { "code": "SCR", "name": "Seychelles Rupee", "description": "", "withdrawn": false },
  { "code": "SDG", "name": "Sudanese Pound", "description": "", "withdrawn": false },
  { "code": "SEK", "name": "Swedish Krona", "description": "", "withdrawn": false },
  { "code": "SGD", "name": "Singapore Dollar", "description": "", "withdrawn": false },
  { "code": "SHP", "name": "Saint Helena Pound", "description": "", "withdrawn": false },
  { "code": "SLE", "name": "Leone", "description": "", "withdrawn": false },
  { "code": "SLL", "name": "Leone", "description": "", "withdrawn": false },
  { "code": "SOS", "name": "Somali Shilling", "description": "", "withdrawn": false },
  { "code": "SSP", "name": "South Sudanese Pound", "description": "", "withdrawn": false },
  { "code": "SRD", "name": "Surinam Dollar", "description": "", "withdrawn": false },
  { "code": "STD", "name": "Dobra", "description": "Withdrawn from ISO Currency codelist. Use code STN.", "withdrawn": true },
  { "code": "STN", "name": "Dobra", "description": "", "withdrawn": false },
  { "code": "SVC", "name": "El Salvador Colon", "description": "", "withdrawn": false },
  { "code": "SYP", "name": "Syrian Pound", "description": "", "withdrawn": false },
  { "code": "SZL", "name": "Lilangeni", "description": "", "withdrawn": false },
  { "code": "THB", "name": "Baht", "description": "", "withdrawn": false },
  { "code": "TJS", "name": "Somoni", "description": "", "withdrawn": false },
  { "code": "TMT", "name": "Manat", "description": "", "withdrawn": false },
  { "code": "TND", "name": "Tunisian Dinar", "description": "", "withdrawn": false },
  { "code": "TOP", "name": "Paanga", "description": "", "withdrawn": false },
  { "code": "TRY", "name": "Turkish Lira", "description": "", "withdrawn": false },
  { "code": "TTD", "name": "Trinidad and Tobago Dollar", "description": "", "withdrawn": false },
  { "code": "TWD", "name": "New Taiwan Dollar", "description": "", "withdrawn": false },
  { "code": "TZS", "name": "Tanzanian Shilling", "description": "", "withdrawn": false },
  { "code": "UAH", "name": "Hryvnia", "description": "", "withdrawn": false },
  { "code": "UGX", "name": "Uganda Shilling", "description": "", "withdrawn": false },
  { "code": "USD", "name": "US Dollar", "description": "", "withdrawn": false },
  { "code": "USN", "name": "US Dollar (Next day)", "description": "", "withdrawn": false },
  { "code": "USS", "name": "US Dollar (Same day)", "description": "Withdrawn from ISO Currency codelist.", "withdrawn": true },
  { "code": "UYI", "name": "Uruguay Peso en Unidades Indexadas", "description": "", "withdrawn": false },
  { "code": "UYU", "name": "Peso Uruguayo", "description": "", "withdrawn": false },
  { "code": "UZS", "name": "Uzbekistan Sum", "description": "", "withdrawn": false },
  { "code": "VED", "name": "Bolivar Soberano", "description": "", "withdrawn": false },
  { "code": "VEF", "name": "Bolivar", "description": "", "withdrawn": true },
  { "code": "VES", "name": "Bolivar Soberano", "description": "", "withdrawn": false },
  { "code": "VND", "name": "Dong", "description": "", "withdrawn": false },
  { "code": "VUV", "name": "Vatu", "description": "", "withdrawn": false },
  { "code": "WST", "name": "Tala", "description": "", "withdrawn": false },
  { "code": "XAF", "name": "CFA Franc BEAC", "description": "", "withdrawn": false },
  { "code": "XBT", "name": "Bitcoin", "description": "", "withdrawn": false },
  { "code": "XCD", "name": "East Caribbean Dollar", "description": "", "withdrawn": false },
  { "code": "XDR", "name": "International Monetary Fund (IMF) Special Drawing Right (SDR)", "description": "", "withdrawn": false },
  { "code": "XOF", "name": "CFA Franc BCEAO", "description": "", "withdrawn": false },
  { "code": "XPF", "name": "CFP Franc", "description": "", "withdrawn": false },
  { "code": "YER", "name": "Yemeni Rial", "description": "", "withdrawn": false },
  { "code": "ZAR", "name": "Rand", "description": "", "withdrawn": false },
  { "code": "ZMK", "name": "Zambian Kwacha", "description": "Withdrawn from ISO Country codelist. Use code ZMW.", "withdrawn": true },
  { "code": "ZMW", "name": "Zambian Kwacha", "description": "", "withdrawn": false },
  { "code": "ZWL", "name": "Zimbabwe Dollar", "description": "", "withdrawn": false }
] 